<?xml version='1.0' encoding='utf-8'?>
<TextureAtlas imagePath="maro.png">
<SubTexture name="maro0000" x="128" y="0" width="64" height="82" frameX="-18" frameY="-18" frameWidth="96" frameHeight="96" />
<SubTexture name="maro0001" x="0" y="88" width="64" height="82" frameX="-18" frameY="-18" frameWidth="96" frameHeight="96" />
<SubTexture name="maro0002" x="64" y="88" width="64" height="82" frameX="-18" frameY="-18" frameWidth="96" frameHeight="96" />
<SubTexture name="maro0003" x="128" y="88" width="64" height="82" frameX="-18" frameY="-18" frameWidth="96" frameHeight="96" />
<SubTexture name="maro0004" x="192" y="0" width="64" height="82" frameX="-18" frameY="-18" frameWidth="96" frameHeight="96" />
<SubTexture name="maro0005" x="192" y="82" width="64" height="82" frameX="-18" frameY="-18" frameWidth="96" frameHeight="96" />
<SubTexture name="maro0006" x="0" y="170" width="64" height="82" frameX="-18" frameY="-18" frameWidth="96" frameHeight="96" />
<SubTexture name="maro0007" x="454" y="498" width="70" height="76" frameX="-18" frameY="-24" frameWidth="96" frameHeight="96" />
<SubTexture name="maro0008" x="524" y="498" width="64" height="76" frameX="-18" frameY="-24" frameWidth="96" frameHeight="96" />
<SubTexture name="maro0009" x="478" y="416" width="58" height="76" frameX="-18" frameY="-24" frameWidth="96" frameHeight="96" />
<SubTexture name="maro0010" x="606" y="0" width="58" height="76" frameX="-24" frameY="-24" frameWidth="96" frameHeight="96" />
<SubTexture name="maro0011" x="606" y="76" width="58" height="76" frameX="-24" frameY="-24" frameWidth="96" frameHeight="96" />
<SubTexture name="maro0012" x="606" y="152" width="58" height="76" frameX="-24" frameY="-24" frameWidth="96" frameHeight="96" />
<SubTexture name="maro0013" x="0" y="580" width="64" height="76" frameX="-18" frameY="-24" frameWidth="96" frameHeight="96" />
<SubTexture name="maro0014" x="64" y="580" width="64" height="76" frameX="-18" frameY="-24" frameWidth="96" frameHeight="96" />
<SubTexture name="maro0015" x="128" y="580" width="70" height="76" frameX="-12" frameY="-24" frameWidth="96" frameHeight="96" />
<SubTexture name="maro0016" x="606" y="228" width="58" height="76" frameX="-12" frameY="-24" frameWidth="96" frameHeight="96" />
<SubTexture name="maro0017" x="606" y="304" width="58" height="76" frameX="-12" frameY="-24" frameWidth="96" frameHeight="96" />
<SubTexture name="maro0018" x="606" y="380" width="58" height="76" frameX="-12" frameY="-24" frameWidth="96" frameHeight="96" />
<SubTexture name="maro0019" x="198" y="580" width="64" height="76" frameX="-12" frameY="-24" frameWidth="96" frameHeight="96" />
<SubTexture name="maro0020" x="606" y="456" width="58" height="76" frameX="-12" frameY="-24" frameWidth="96" frameHeight="96" />
<SubTexture name="maro0021" x="262" y="580" width="58" height="76" frameX="-24" frameY="-24" frameWidth="96" frameHeight="96" />
<SubTexture name="maro0022" x="320" y="580" width="64" height="76" frameX="-18" frameY="-24" frameWidth="96" frameHeight="96" />
<SubTexture name="maro0023" x="384" y="580" width="64" height="76" frameX="-18" frameY="-24" frameWidth="96" frameHeight="96" />
<SubTexture name="maro0024" x="448" y="580" width="64" height="76" frameX="-18" frameY="-24" frameWidth="96" frameHeight="96" />
<SubTexture name="maro0025" x="512" y="580" width="64" height="76" frameX="-18" frameY="-24" frameWidth="96" frameHeight="96" />
<SubTexture name="maro0026" x="576" y="580" width="58" height="76" frameX="-24" frameY="-24" frameWidth="96" frameHeight="96" />
<SubTexture name="maro0027" x="664" y="0" width="58" height="76" frameX="-24" frameY="-24" frameWidth="96" frameHeight="96" />
<SubTexture name="maro0028" x="664" y="76" width="58" height="76" frameX="-24" frameY="-24" frameWidth="96" frameHeight="96" />
<SubTexture name="maro0029" x="664" y="152" width="58" height="76" frameX="-24" frameY="-24" frameWidth="96" frameHeight="96" />
<SubTexture name="maro0030" x="664" y="228" width="58" height="76" frameX="-24" frameY="-24" frameWidth="96" frameHeight="96" />
<SubTexture name="maro0031" x="664" y="304" width="58" height="76" frameX="-24" frameY="-24" frameWidth="96" frameHeight="96" />
<SubTexture name="maro0032" x="722" y="0" width="64" height="76" frameX="-12" frameY="-24" frameWidth="96" frameHeight="96" />
<SubTexture name="maro0033" x="722" y="76" width="58" height="76" frameX="-12" frameY="-24" frameWidth="96" frameHeight="96" />
<SubTexture name="maro0034" x="722" y="152" width="58" height="76" frameX="-12" frameY="-24" frameWidth="96" frameHeight="96" />
<SubTexture name="maro0035" x="722" y="228" width="64" height="76" frameX="-12" frameY="-24" frameWidth="96" frameHeight="96" />
<SubTexture name="maro0036" x="722" y="304" width="64" height="76" frameX="-12" frameY="-24" frameWidth="96" frameHeight="96" />
<SubTexture name="maro0037" x="722" y="380" width="64" height="76" frameX="-18" frameY="-24" frameWidth="96" frameHeight="96" />
<SubTexture name="maro0038" x="0" y="656" width="70" height="76" frameX="-18" frameY="-24" frameWidth="96" frameHeight="96" />
<SubTexture name="maro0039" x="722" y="456" width="64" height="76" frameX="-18" frameY="-24" frameWidth="96" frameHeight="96" />
<SubTexture name="maro0040" x="70" y="656" width="70" height="76" frameX="-18" frameY="-24" frameWidth="96" frameHeight="96" />
<SubTexture name="maro0041" x="722" y="532" width="58" height="76" frameX="-24" frameY="-24" frameWidth="96" frameHeight="96" />
<SubTexture name="maro0042" x="140" y="656" width="64" height="76" frameX="-18" frameY="-24" frameWidth="96" frameHeight="96" />
<SubTexture name="maro0043" x="204" y="656" width="64" height="76" frameX="-12" frameY="-24" frameWidth="96" frameHeight="96" />
<SubTexture name="maro0044" x="664" y="380" width="58" height="76" frameX="-12" frameY="-24" frameWidth="96" frameHeight="96" />
<SubTexture name="maro0045" x="664" y="456" width="58" height="76" frameX="-12" frameY="-24" frameWidth="96" frameHeight="96" />
<SubTexture name="maro0046" x="664" y="532" width="58" height="76" frameX="-12" frameY="-24" frameWidth="96" frameHeight="96" />
<SubTexture name="maro0047" x="268" y="656" width="58" height="76" frameX="-12" frameY="-24" frameWidth="96" frameHeight="96" />
<SubTexture name="maro0048" x="64" y="170" width="58" height="82" frameX="-6" frameY="-18" frameWidth="96" frameHeight="96" />
<SubTexture name="maro0049" x="326" y="656" width="58" height="76" frameX="-6" frameY="-24" frameWidth="96" frameHeight="96" />
<SubTexture name="maro0050" x="384" y="656" width="64" height="76" frameX="-6" frameY="-24" frameWidth="96" frameHeight="96" />
<SubTexture name="maro0051" x="448" y="656" width="64" height="76" frameX="-6" frameY="-24" frameWidth="96" frameHeight="96" />
<SubTexture name="maro0052" x="122" y="170" width="70" height="82" frameX="-12" frameY="-18" frameWidth="96" frameHeight="96" />
<SubTexture name="maro0053" x="256" y="0" width="76" height="82" frameX="-6" frameY="-18" frameWidth="96" frameHeight="96" />
<SubTexture name="maro0054" x="512" y="656" width="76" height="76" frameX="-12" frameY="-24" frameWidth="96" frameHeight="96" />
<SubTexture name="maro0055" x="588" y="656" width="70" height="76" frameX="-18" frameY="-24" frameWidth="96" frameHeight="96" />
<SubTexture name="maro0056" x="256" y="82" width="70" height="82" frameX="-18" frameY="-18" frameWidth="96" frameHeight="96" />
<SubTexture name="maro0057" x="256" y="164" width="70" height="82" frameX="-12" frameY="-18" frameWidth="96" frameHeight="96" />
<SubTexture name="maro0058" x="332" y="0" width="76" height="82" frameX="-6" frameY="-18" frameWidth="96" frameHeight="96" />
<SubTexture name="maro0059" x="332" y="82" width="64" height="82" frameX="-6" frameY="-18" frameWidth="96" frameHeight="96" />
<SubTexture name="maro0060" x="658" y="656" width="64" height="76" frameX="-12" frameY="-24" frameWidth="96" frameHeight="96" />
<SubTexture name="maro0061" x="722" y="656" width="64" height="76" frameX="-12" frameY="-24" frameWidth="96" frameHeight="96" />
<SubTexture name="maro0062" x="332" y="164" width="64" height="82" frameX="-12" frameY="-18" frameWidth="96" frameHeight="96" />
<SubTexture name="maro0063" x="0" y="252" width="76" height="82" frameX="-6" frameY="-18" frameWidth="96" frameHeight="96" />
<SubTexture name="maro0064" x="786" y="0" width="70" height="76" frameX="-12" frameY="-24" frameWidth="96" frameHeight="96" />
<SubTexture name="maro0065" x="786" y="76" width="70" height="76" frameX="-12" frameY="-24" frameWidth="96" frameHeight="96" />
<SubTexture name="maro0066" x="192" y="170" width="64" height="82" frameX="-18" frameY="-18" frameWidth="96" frameHeight="96" />
<SubTexture name="maro0067" x="76" y="252" width="76" height="82" frameX="-6" frameY="-18" frameWidth="96" frameHeight="96" />
<SubTexture name="maro0068" x="152" y="252" width="82" height="82" frameX="-6" frameY="-18" frameWidth="96" frameHeight="96" />
<SubTexture name="maro0069" x="234" y="252" width="76" height="82" frameX="-12" frameY="-18" frameWidth="96" frameHeight="96" />
<SubTexture name="maro0070" x="786" y="152" width="70" height="76" frameX="-18" frameY="-24" frameWidth="96" frameHeight="96" />
<SubTexture name="maro0071" x="786" y="228" width="70" height="76" frameX="-18" frameY="-24" frameWidth="96" frameHeight="96" />
<SubTexture name="maro0072" x="310" y="252" width="70" height="82" frameX="-18" frameY="-18" frameWidth="96" frameHeight="96" />
<SubTexture name="maro0073" x="0" y="0" width="70" height="88" frameX="-12" frameY="-12" frameWidth="96" frameHeight="96" />
<SubTexture name="maro0074" x="786" y="304" width="64" height="76" frameX="-12" frameY="-24" frameWidth="96" frameHeight="96" />
<SubTexture name="maro0075" x="786" y="380" width="64" height="76" frameX="-12" frameY="-24" frameWidth="96" frameHeight="96" />
<SubTexture name="maro0076" x="786" y="456" width="64" height="76" frameX="-12" frameY="-24" frameWidth="96" frameHeight="96" />
<SubTexture name="maro0077" x="408" y="0" width="64" height="82" frameX="-12" frameY="-18" frameWidth="96" frameHeight="96" />
<SubTexture name="maro0078" x="0" y="732" width="76" height="76" frameX="-6" frameY="-24" frameWidth="96" frameHeight="96" />
<SubTexture name="maro0079" x="0" y="334" width="76" height="82" frameX="-6" frameY="-18" frameWidth="96" frameHeight="96" />
<SubTexture name="maro0080" x="76" y="334" width="70" height="82" frameX="-12" frameY="-18" frameWidth="96" frameHeight="96" />
<SubTexture name="maro0081" x="786" y="532" width="64" height="76" frameX="-18" frameY="-24" frameWidth="96" frameHeight="96" />
<SubTexture name="maro0082" x="408" y="82" width="64" height="82" frameX="-18" frameY="-18" frameWidth="96" frameHeight="96" />
<SubTexture name="maro0083" x="146" y="334" width="70" height="82" frameX="-12" frameY="-18" frameWidth="96" frameHeight="96" />
<SubTexture name="maro0084" x="216" y="334" width="70" height="82" frameX="-6" frameY="-18" frameWidth="96" frameHeight="96" />
<SubTexture name="maro0085" x="408" y="164" width="58" height="82" frameX="-12" frameY="-18" frameWidth="96" frameHeight="96" />
<SubTexture name="maro0086" x="408" y="246" width="58" height="82" frameX="-12" frameY="-18" frameWidth="96" frameHeight="96" />
<SubTexture name="maro0087" x="70" y="0" width="58" height="88" frameX="-12" frameY="-12" frameWidth="96" frameHeight="96" />
<SubTexture name="maro0088" x="286" y="334" width="64" height="82" frameX="-6" frameY="-18" frameWidth="96" frameHeight="96" />
<SubTexture name="maro0089" x="350" y="334" width="64" height="82" frameX="-6" frameY="-18" frameWidth="96" frameHeight="96" />
<SubTexture name="maro0090" x="472" y="0" width="64" height="82" frameX="-6" frameY="-18" frameWidth="96" frameHeight="96" />
<SubTexture name="maro0091" x="786" y="608" width="64" height="76" frameX="-6" frameY="-24" frameWidth="96" frameHeight="96" />
<SubTexture name="maro0092" x="76" y="732" width="64" height="76" frameX="-6" frameY="-24" frameWidth="96" frameHeight="96" />
<SubTexture name="maro0093" x="140" y="732" width="70" height="76" frameX="0" frameY="-24" frameWidth="96" frameHeight="96" />
<SubTexture name="maro0094" x="0" y="416" width="70" height="82" frameX="0" frameY="-18" frameWidth="96" frameHeight="96" />
<SubTexture name="maro0095" x="70" y="416" width="70" height="82" frameX="-6" frameY="-18" frameWidth="96" frameHeight="96" />
<SubTexture name="maro0096" x="210" y="732" width="70" height="76" frameX="-12" frameY="-24" frameWidth="96" frameHeight="96" />
<SubTexture name="maro0097" x="280" y="732" width="64" height="76" frameX="-18" frameY="-24" frameWidth="96" frameHeight="96" />
<SubTexture name="maro0098" x="344" y="732" width="64" height="76" frameX="-18" frameY="-24" frameWidth="96" frameHeight="96" />
<SubTexture name="maro0099" x="408" y="732" width="70" height="76" frameX="-12" frameY="-24" frameWidth="96" frameHeight="96" />
<SubTexture name="maro0100" x="478" y="732" width="64" height="76" frameX="-18" frameY="-24" frameWidth="96" frameHeight="96" />
<SubTexture name="maro0101" x="542" y="732" width="64" height="76" frameX="-24" frameY="-24" frameWidth="96" frameHeight="96" />
<SubTexture name="maro0102" x="606" y="732" width="58" height="76" frameX="-30" frameY="-24" frameWidth="96" frameHeight="96" />
<SubTexture name="maro0103" x="664" y="732" width="64" height="76" frameX="-30" frameY="-24" frameWidth="96" frameHeight="96" />
<SubTexture name="maro0104" x="728" y="732" width="70" height="76" frameX="-24" frameY="-24" frameWidth="96" frameHeight="96" />
<SubTexture name="maro0105" x="856" y="0" width="64" height="76" frameX="-30" frameY="-24" frameWidth="96" frameHeight="96" />
<SubTexture name="maro0106" x="856" y="76" width="64" height="76" frameX="-30" frameY="-24" frameWidth="96" frameHeight="96" />
<SubTexture name="maro0107" x="856" y="152" width="58" height="76" frameX="-42" frameY="-24" frameWidth="96" frameHeight="96" />
<SubTexture name="maro0108" x="472" y="82" width="58" height="82" frameX="-42" frameY="-18" frameWidth="96" frameHeight="96" />
<SubTexture name="maro0109" x="856" y="228" width="58" height="76" frameX="-42" frameY="-24" frameWidth="96" frameHeight="96" />
<SubTexture name="maro0110" x="856" y="304" width="64" height="76" frameX="-36" frameY="-24" frameWidth="96" frameHeight="96" />
<SubTexture name="maro0111" x="856" y="380" width="64" height="76" frameX="-36" frameY="-24" frameWidth="96" frameHeight="96" />
<SubTexture name="maro0112" x="472" y="164" width="64" height="82" frameX="-36" frameY="-18" frameWidth="96" frameHeight="96" />
<SubTexture name="maro0113" x="472" y="246" width="64" height="82" frameX="-36" frameY="-18" frameWidth="96" frameHeight="96" />
<SubTexture name="maro0114" x="472" y="328" width="58" height="82" frameX="-42" frameY="-18" frameWidth="96" frameHeight="96" />
<SubTexture name="maro0115" x="856" y="456" width="58" height="76" frameX="-42" frameY="-24" frameWidth="96" frameHeight="96" />
<SubTexture name="maro0116" x="856" y="532" width="58" height="76" frameX="-42" frameY="-24" frameWidth="96" frameHeight="96" />
<SubTexture name="maro0117" x="414" y="334" width="58" height="82" frameX="-42" frameY="-18" frameWidth="96" frameHeight="96" />
<SubTexture name="maro0118" x="140" y="416" width="64" height="82" frameX="-36" frameY="-18" frameWidth="96" frameHeight="96" />
<SubTexture name="maro0119" x="204" y="416" width="70" height="82" frameX="-30" frameY="-18" frameWidth="96" frameHeight="96" />
<SubTexture name="maro0120" x="274" y="416" width="70" height="82" frameX="-30" frameY="-18" frameWidth="96" frameHeight="96" />
<SubTexture name="maro0121" x="344" y="416" width="64" height="82" frameX="-36" frameY="-18" frameWidth="96" frameHeight="96" />
<SubTexture name="maro0122" x="408" y="416" width="70" height="82" frameX="-30" frameY="-18" frameWidth="96" frameHeight="96" />
<SubTexture name="maro0123" x="536" y="0" width="70" height="82" frameX="-30" frameY="-18" frameWidth="96" frameHeight="96" />
<SubTexture name="maro0124" x="536" y="82" width="64" height="82" frameX="-24" frameY="-18" frameWidth="96" frameHeight="96" />
<SubTexture name="maro0125" x="536" y="164" width="64" height="82" frameX="-24" frameY="-18" frameWidth="96" frameHeight="96" />
<SubTexture name="maro0126" x="856" y="608" width="64" height="76" frameX="-24" frameY="-24" frameWidth="96" frameHeight="96" />
<SubTexture name="maro0127" x="856" y="684" width="64" height="76" frameX="-24" frameY="-24" frameWidth="96" frameHeight="96" />
<SubTexture name="maro0128" x="536" y="246" width="64" height="82" frameX="-24" frameY="-18" frameWidth="96" frameHeight="96" />
<SubTexture name="maro0129" x="0" y="808" width="64" height="76" frameX="-18" frameY="-24" frameWidth="96" frameHeight="96" />
<SubTexture name="maro0130" x="64" y="808" width="64" height="76" frameX="-12" frameY="-24" frameWidth="96" frameHeight="96" />
<SubTexture name="maro0131" x="536" y="328" width="70" height="82" frameX="-12" frameY="-18" frameWidth="96" frameHeight="96" />
<SubTexture name="maro0132" x="128" y="808" width="70" height="76" frameX="-12" frameY="-24" frameWidth="96" frameHeight="96" />
<SubTexture name="maro0133" x="536" y="410" width="70" height="82" frameX="-12" frameY="-18" frameWidth="96" frameHeight="96" />
<SubTexture name="maro0134" x="198" y="808" width="70" height="76" frameX="-12" frameY="-24" frameWidth="96" frameHeight="96" />
<SubTexture name="maro0135" x="268" y="808" width="70" height="76" frameX="-12" frameY="-24" frameWidth="96" frameHeight="96" />
<SubTexture name="maro0136" x="338" y="808" width="70" height="76" frameX="-12" frameY="-24" frameWidth="96" frameHeight="96" />
<SubTexture name="maro0137" x="408" y="808" width="70" height="76" frameX="-12" frameY="-24" frameWidth="96" frameHeight="96" />
<SubTexture name="maro0138" x="0" y="498" width="70" height="82" frameX="-12" frameY="-18" frameWidth="96" frameHeight="96" />
<SubTexture name="maro0139" x="70" y="498" width="64" height="82" frameX="-18" frameY="-18" frameWidth="96" frameHeight="96" />
<SubTexture name="maro0140" x="134" y="498" width="64" height="82" frameX="-18" frameY="-18" frameWidth="96" frameHeight="96" />
<SubTexture name="maro0141" x="198" y="498" width="64" height="82" frameX="-18" frameY="-18" frameWidth="96" frameHeight="96" />
<SubTexture name="maro0142" x="262" y="498" width="64" height="82" frameX="-18" frameY="-18" frameWidth="96" frameHeight="96" />
<SubTexture name="maro0143" x="326" y="498" width="64" height="82" frameX="-18" frameY="-18" frameWidth="96" frameHeight="96" />
<SubTexture name="maro0144" x="128" y="0" width="64" height="82" frameX="-18" frameY="-18" frameWidth="96" frameHeight="96" />
<SubTexture name="maro0145" x="390" y="498" width="64" height="82" frameX="-18" frameY="-18" frameWidth="96" frameHeight="96" />
</TextureAtlas>
